ai_plays_jackbox/__init__.py
ai_plays_jackbox/bot/__init__.py
ai_plays_jackbox/bot/bot_base.py
ai_plays_jackbox/bot/bot_factory.py
ai_plays_jackbox/bot/bot_personality.py
ai_plays_jackbox/bot/jackbox5/__init__.py
ai_plays_jackbox/bot/jackbox5/bot_base.py
ai_plays_jackbox/bot/jackbox5/mad_verse_city.py
ai_plays_jackbox/bot/jackbox5/patently_stupid.py
ai_plays_jackbox/bot/jackbox6/__init__.py
ai_plays_jackbox/bot/jackbox6/bot_base.py
ai_plays_jackbox/bot/jackbox6/dictionarium.py
ai_plays_jackbox/bot/jackbox6/joke_boat.py
ai_plays_jackbox/bot/jackbox7/__init__.py
ai_plays_jackbox/bot/jackbox7/bot_base.py
ai_plays_jackbox/bot/jackbox7/quiplash3.py
ai_plays_jackbox/bot/jackbox8/__init__.py
ai_plays_jackbox/bot/jackbox8/bot_base.py
ai_plays_jackbox/bot/jackbox8/job_job.py
ai_plays_jackbox/bot/standalone/__init__.py
ai_plays_jackbox/bot/standalone/drawful2.py
ai_plays_jackbox/cli/__init__.py
ai_plays_jackbox/cli/main.py
ai_plays_jackbox/constants.py
ai_plays_jackbox/llm/__init__.py
ai_plays_jackbox/llm/chat_model.py
ai_plays_jackbox/llm/chat_model_factory.py
ai_plays_jackbox/llm/gemini_model.py
ai_plays_jackbox/llm/ollama_model.py
ai_plays_jackbox/llm/openai_model.py
ai_plays_jackbox/room/__init__.py
ai_plays_jackbox/room/room.py
ai_plays_jackbox/run.py
ai_plays_jackbox/scripts/lint.py
ai_plays_jackbox/ui/__init__.py
ai_plays_jackbox/ui/main.py
ai_plays_jackbox/ui/startup.py
ai_plays_jackbox-0.4.1.dist-info/METADATA
ai_plays_jackbox-0.4.1.dist-info/WHEEL
ai_plays_jackbox-0.4.1.dist-info/entry_points.txt
ai_plays_jackbox-0.4.1.dist-info/licenses/LICENSE
ai_plays_jackbox-0.4.1.dist-info/RECORD
