Metadata-Version: 2.4
Name: ai-plays-jackbox
Version: 0.4.1
Summary: Bringing the dead internet theory to life. Have AI play JackBox with you; no friends required!
License: MIT
License-File: LICENSE
Author: Daniel S. Thompson
Author-email: dthomp92@gmail.com
Requires-Python: >=3.11,<4.0
Classifier: License :: OSI Approved :: MIT License
Classifier: Programming Language :: Python :: 3
Classifier: Programming Language :: Python :: 3.11
Classifier: Programming Language :: Python :: 3.12
Classifier: Programming Language :: Python :: 3.13
Classifier: Programming Language :: Python :: 3.14
Requires-Dist: demoji (>=1.1.0,<2.0.0)
Requires-Dist: google-genai (>=1.19.0,<2.0.0)
Requires-Dist: html2text (>=2025.4.15,<2026.0.0)
Requires-Dist: loguru (>=0.7.3,<1.0.0)
Requires-Dist: nicegui (>=3.4.1,<4.0.0)
Requires-Dist: numpy (>=2.4.0,<3.0.0)
Requires-Dist: ollama (>=0.4.4,<1.0.0)
Requires-Dist: openai (>=2.14.0,<3.0.0)
Requires-Dist: opencv-python (>=4.11.0.86,<5.0.0.0)
Requires-Dist: psutil (>=7.0.0,<8.0.0)
Requires-Dist: pydantic (>=2.10.4,<3.0.0)
Requires-Dist: requests (>=2.23.3,<3.0.0)
Requires-Dist: websocket-client (>=1.8.0,<2.0.0)
Project-URL: Bug Tracker, https://github.com/SudoSpartanDan/AIPlaysJackBox/issues
Project-URL: Repository, https://github.com/SudoSpartanDan/AIPlaysJackBox
